py_polymorphic_list/__init__.py
py_polymorphic_list/exceptions.py
py_polymorphic_list/polymorphic_list.py
py_polymorphic_list-1.0.0.dist-info/METADATA
py_polymorphic_list-1.0.0.dist-info/WHEEL
py_polymorphic_list-1.0.0.dist-info/top_level.txt
py_polymorphic_list-1.0.0.dist-info/RECORD
