Metadata-Version: 2.1
Name: py-polymorphic-list
Version: 1.0.0
Summary: Python implementation of a polymorphic list
Home-page: https://github.com/keshprad/py_polymorphic_list
Author: keshprad
Author-email: keshprad.dev@gmail.com
License: UNKNOWN
Keywords: polymorphic-list
Platform: UNKNOWN
